{
  "region": "g20",
  "snapshot_date": "2026-05-16",
  "leaders": {
    "indonesia": {
      "country": {
        "iso_code": "ID",
        "name_en": "Indonesia",
        "name_local": "Indonesia"
      },
      "head_of_government": {
        "title": "President",
        "name": "Prabowo Subianto",
        "name_local": "Prabowo Subianto",
        "since": "2024-10-20"
      },
      "head_of_state": {
        "title": "President",
        "name": "Prabowo Subianto",
        "name_local": "Prabowo Subianto",
        "since": "2024-10-20"
      }
    },
    "argentina": {
      "country": {
        "iso_code": "AR",
        "name_en": "Argentina",
        "name_local": "Argentina"
      },
      "head_of_government": {
        "title": "President",
        "name": "Javier Milei",
        "name_local": "Javier Milei",
        "since": "2023-12-10"
      },
      "head_of_state": {
        "title": "President",
        "name": "Javier Milei",
        "name_local": "Javier Milei",
        "since": "2023-12-10"
      }
    },
    "australia": {
      "country": {
        "iso_code": "AU",
        "name_en": "Australia",
        "name_local": "Australia"
      },
      "head_of_government": {
        "title": "Prime Minister",
        "name": "Anthony Albanese",
        "name_local": null,
        "since": "2022-05-23"
      },
      "head_of_state": {
        "title": "Monarch",
        "name": "Charles III",
        "name_local": null,
        "since": "2022-09-08"
      }
    },
    "brazil": {
      "country": {
        "iso_code": "BR",
        "name_en": "Brazil",
        "name_local": "Brasil"
      },
      "head_of_government": {
        "title": "President",
        "name": "Luiz Inácio Lula da Silva",
        "name_local": "Luiz Inácio Lula da Silva",
        "since": "2023-01-01"
      },
      "head_of_state": {
        "title": "President",
        "name": "Luiz Inácio Lula da Silva",
        "name_local": "Luiz Inácio Lula da Silva",
        "since": "2023-01-01"
      }
    },
    "canada": {
      "country": {
        "iso_code": "CA",
        "name_en": "Canada",
        "name_local": "Canada"
      },
      "head_of_government": {
        "title": "Prime Minister",
        "name": "Mark Carney",
        "name_local": null,
        "since": null
      },
      "head_of_state": {
        "title": "Monarch",
        "name": "Charles III",
        "name_local": null,
        "since": "2022-09-08"
      }
    },
    "china": {
      "country": {
        "iso_code": "CN",
        "name_en": "China",
        "name_local": "中国"
      },
      "head_of_government": {
        "title": "Premier",
        "name": "Li Qiang",
        "name_local": "李强",
        "since": "2023-03-11"
      },
      "head_of_state": {
        "title": "President",
        "name": "Xi Jinping",
        "name_local": "习近平",
        "since": "2013-03-14"
      }
    },
    "france": {
      "country": {
        "iso_code": "FR",
        "name_en": "France",
        "name_local": "France"
      },
      "head_of_government": {
        "title": "Prime Minister",
        "name": "Sébastien Lecornu",
        "name_local": "Sébastien Lecornu",
        "since": "2025-09-09"
      },
      "head_of_state": {
        "title": "President",
        "name": "Emmanuel Macron",
        "name_local": "Emmanuel Macron",
        "since": "2017-05-14"
      }
    },
    "germany": {
      "country": {
        "iso_code": "DE",
        "name_en": "Germany",
        "name_local": "Deutschland"
      },
      "head_of_government": {
        "title": "Chancellor",
        "name": "Friedrich Merz",
        "name_local": "Friedrich Merz",
        "since": "2025-05-06"
      },
      "head_of_state": {
        "title": "President",
        "name": "Frank-Walter Steinmeier",
        "name_local": "Frank-Walter Steinmeier",
        "since": "2017-03-19"
      }
    },
    "india": {
      "country": {
        "iso_code": "IN",
        "name_en": "India",
        "name_local": "भारत"
      },
      "head_of_government": {
        "title": "Prime Minister",
        "name": "Narendra Modi",
        "name_local": "नरेन्द्र मोदी",
        "since": "2014-05-26"
      },
      "head_of_state": {
        "title": "President",
        "name": "Droupadi Murmu",
        "name_local": "द्रौपदी मुर्मू",
        "since": "2022-07-25"
      }
    },
    "italy": {
      "country": {
        "iso_code": "IT",
        "name_en": "Italy",
        "name_local": "Italia"
      },
      "head_of_government": {
        "title": "Prime Minister",
        "name": "Giorgia Meloni",
        "name_local": "Giorgia Meloni",
        "since": "2022-10-22"
      },
      "head_of_state": {
        "title": "President",
        "name": "Sergio Mattarella",
        "name_local": "Sergio Mattarella",
        "since": "2015-02-03"
      }
    },
    "japan": {
      "country": {
        "iso_code": "JP",
        "name_en": "Japan",
        "name_local": "日本"
      },
      "head_of_government": {
        "title": "Prime Minister",
        "name": "Sanae Takaichi",
        "name_local": "高市早苗",
        "since": "2025-10-21"
      },
      "head_of_state": {
        "title": "Emperor",
        "name": "Naruhito",
        "name_local": "徳仁",
        "since": "2019-05-01"
      }
    },
    "mexico": {
      "country": {
        "iso_code": "MX",
        "name_en": "Mexico",
        "name_local": "México"
      },
      "head_of_government": {
        "title": "President",
        "name": "Claudia Sheinbaum",
        "name_local": null,
        "since": "2024-10-01"
      },
      "head_of_state": {
        "title": "President",
        "name": "Claudia Sheinbaum",
        "name_local": null,
        "since": "2024-10-01"
      }
    },
    "russia": {
      "country": {
        "iso_code": "RU",
        "name_en": "Russia",
        "name_local": "Россия"
      },
      "head_of_government": {
        "title": "Prime Minister",
        "name": "Mikhail Mishustin",
        "name_local": "Михаил Владимирович Мишустин",
        "since": "2020-01-16"
      },
      "head_of_state": {
        "title": "President",
        "name": "Vladimir Putin",
        "name_local": "Владимир Владимирович Путин",
        "since": "2012-05-07"
      }
    },
    "saudi_arabia": {
      "country": {
        "iso_code": "SA",
        "name_en": "Saudi Arabia",
        "name_local": "المملكة العربية السعودية"
      },
      "head_of_government": {
        "title": "Prime Minister (King)",
        "name": "Mohammed bin Salman",
        "name_local": "محمد بن سلمان آل سعود",
        "since": "2022-09-27"
      },
      "head_of_state": {
        "title": "King",
        "name": "Mohammed bin Salman",
        "name_local": "محمد بن سلمان آل سعود",
        "since": "2022-09-27"
      }
    },
    "south_africa": {
      "country": {
        "iso_code": "ZA",
        "name_en": "South Africa",
        "name_local": "South Africa"
      },
      "head_of_government": {
        "title": "President",
        "name": "Cyril Ramaphosa",
        "name_local": null,
        "since": "2018-02-15"
      },
      "head_of_state": {
        "title": "President",
        "name": "Cyril Ramaphosa",
        "name_local": null,
        "since": "2018-02-15"
      }
    },
    "south_korea": {
      "country": {
        "iso_code": "KR",
        "name_en": "South Korea",
        "name_local": "대한민국"
      },
      "head_of_government": {
        "title": "President",
        "name": "Lee Jae Myung",
        "name_local": "이재명",
        "since": "2025-06-04"
      },
      "head_of_state": {
        "title": "President",
        "name": "Lee Jae Myung",
        "name_local": "이재명",
        "since": "2025-06-04"
      }
    },
    "turkey": {
      "country": {
        "iso_code": "TR",
        "name_en": "Turkey",
        "name_local": "Türkiye"
      },
      "head_of_government": {
        "title": "President",
        "name": "Recep Tayyip Erdoğan",
        "name_local": "Recep Tayyip Erdoğan",
        "since": "2014-08-28"
      },
      "head_of_state": {
        "title": "President",
        "name": "Recep Tayyip Erdoğan",
        "name_local": "Recep Tayyip Erdoğan",
        "since": "2014-08-28"
      }
    },
    "uk": {
      "country": {
        "iso_code": "GB",
        "name_en": "United Kingdom",
        "name_local": "United Kingdom"
      },
      "head_of_government": {
        "title": "Prime Minister",
        "name": "Keir Starmer",
        "name_local": null,
        "since": "2024-07-05"
      },
      "head_of_state": {
        "title": "Monarch",
        "name": "Charles III",
        "name_local": null,
        "since": "2022-09-08"
      }
    },
    "usa": {
      "country": {
        "iso_code": "US",
        "name_en": "United States",
        "name_local": "United States"
      },
      "head_of_government": {
        "title": "President",
        "name": "Donald Trump",
        "name_local": null,
        "since": "2025-01-20"
      },
      "head_of_state": {
        "title": "President",
        "name": "Donald Trump",
        "name_local": null,
        "since": "2025-01-20"
      }
    },
    "european_union": {
      "country": {
        "iso_code": "EU",
        "name_en": "European Union",
        "name_local": "European Union"
      },
      "head_of_government": {
        "title": "President of the European Commission",
        "name": "Ursula von der Leyen",
        "name_local": null,
        "since": "2019-12-01"
      },
      "head_of_state": {
        "title": "President of the European Council",
        "name": "António Costa",
        "name_local": null,
        "since": "2024-12-01"
      }
    },
    "african_union": {
      "country": {
        "iso_code": "AU_AF",
        "name_en": "African Union",
        "name_local": "African Union"
      },
      "head_of_government": {
        "title": "Chairperson of the African Union Commission",
        "name": "Mahamoud Ali Youssouf",
        "name_local": null,
        "since": "2025-03-13"
      },
      "head_of_state": {
        "title": "Chairperson of the African Union",
        "name": "Évariste Ndayishimiye",
        "name_local": null,
        "since": "2026-02-14"
      }
    }
  }
}